easyNotion/__init__.py
easyNotion/easyNotion.py
easyNotion-0.0.1.dist-info/LICENSE.txt
easyNotion-0.0.1.dist-info/METADATA
easyNotion-0.0.1.dist-info/WHEEL
easyNotion-0.0.1.dist-info/top_level.txt
easyNotion-0.0.1.dist-info/RECORD
