Metadata-Version: 2.1
Name: easyNotion
Version: 0.0.1
Summary: A very easy-to-use Notion API
Home-page: https://github.com/zuo-shi-yun/easy-notion-API
Author: zuoShiYun
Author-email: 2818252801@qq.com
Classifier: Programming Language :: Python :: 3
Classifier: License :: OSI Approved :: MIT License
Classifier: Operating System :: OS Independent
Requires-Python: >=3.6
License-File: LICENSE.txt
